mnemon/__init__.py
mnemon/constants.py
mnemon/dec.py
mnemon/mnemon.py
mnemon-0.1b0.dist-info/DESCRIPTION.rst
mnemon-0.1b0.dist-info/METADATA
mnemon-0.1b0.dist-info/RECORD
mnemon-0.1b0.dist-info/WHEEL
mnemon-0.1b0.dist-info/metadata.json
mnemon-0.1b0.dist-info/top_level.txt
